LICENSE
hamcws/__init__.py
hamcws/hamcws.py
hamcws-0.2.7.dist-info/LICENSE
hamcws-0.2.7.dist-info/METADATA
hamcws-0.2.7.dist-info/WHEEL
hamcws-0.2.7.dist-info/RECORD
