Metadata-Version: 2.1
Name: hamcws
Version: 0.2.7
Summary: homeassistant friendly wrapper for J River MCWS
Home-page: http://github.com/3ll3d00d/hamcws
License: MIT
Author: 3ll3d00d
Author-email: mattkhan+hamcws@gmail.com
Requires-Python: >=3.12,<4.0
Classifier: License :: OSI Approved :: MIT License
Classifier: Programming Language :: Python :: 3
Classifier: Programming Language :: Python :: 3.12
Classifier: Programming Language :: Python :: 3.13
Requires-Dist: aiohttp (>=3.9.1,<4.0.0)
Requires-Dist: pytest (>=8.3.3,<9.0.0)
Project-URL: Repository, http://github.com/3ll3d00d/hamcws
